AlphaFonts/__init__.py
AlphaFonts/capsify.py
capsify-0.4.dist-info/METADATA
capsify-0.4.dist-info/WHEEL
capsify-0.4.dist-info/top_level.txt
capsify-0.4.dist-info/RECORD
