Metadata-Version: 2.2
Name: capsify
Version: 0.4
Summary: A Python package for Capsify Font.
Home-page: https://t.me/North_Yankton
Author: Alpha
Author-email: imr@outlook.in
Classifier: Programming Language :: Python :: 3
Classifier: License :: OSI Approved :: MIT License
Classifier: Operating System :: OS Independent
Requires-Python: >=3.6
Dynamic: author
Dynamic: author-email
Dynamic: classifier
Dynamic: description
Dynamic: description-content-type
Dynamic: home-page
Dynamic: requires-python
Dynamic: summary
